git_status_checker/__init__.py
git_status_checker/__main__.py
git_status_checker/git_status_checker.py
git_status_checker-2020.4.14.dist-info/LICENSE
git_status_checker-2020.4.14.dist-info/METADATA
git_status_checker-2020.4.14.dist-info/WHEEL
git_status_checker-2020.4.14.dist-info/entry_points.txt
git_status_checker-2020.4.14.dist-info/top_level.txt
git_status_checker-2020.4.14.dist-info/RECORD
