Metadata-Version: 2.1
Name: git-status-checker
Version: 2020.4.14
Summary: Check git repositories for uncommitted or unpushed changes.
Home-page: https://github.com/scholer/git-status-checker
Author: Rasmus Scholer Sorensen
Author-email: rasmusscholer@gmail.com
License: GNU General Public License v3 (GPLv3)
Download-URL: https://github.com/scholer/git_status_checker/archive/master.zip
Project-URL: Bug Tracker, https://github.com/scholer/git-status-checker/issues
Project-URL: Source Code, https://github.com/scholer/git-status-checker
Keywords: Git,Version control,Development tools
Platform: UNKNOWN
Classifier: Development Status :: 5 - Production/Stable
Classifier: Environment :: Console
Classifier: Intended Audience :: Developers
Classifier: Intended Audience :: Science/Research
Classifier: Intended Audience :: End Users/Desktop
Classifier: Topic :: Software Development :: Build Tools
Classifier: License :: OSI Approved :: GNU General Public License v3 (GPLv3)
Classifier: Programming Language :: Python
Classifier: Programming Language :: Python :: 3
Classifier: Programming Language :: Python :: 3.6
Classifier: Programming Language :: Python :: 3.7
Classifier: Programming Language :: Python :: 3.8
Classifier: Operating System :: MacOS
Classifier: Operating System :: Microsoft
Classifier: Operating System :: POSIX :: Linux
Requires-Dist: pyyaml
